shocktube1dcalc/__init__.py
shocktube1dcalc/cese.py
shocktube1dcalc/generator_mesh.py
shocktube1dcalc/helper.py
shocktube1dcalc/helper_plot.py
shocktube1dcalc/shocktube1dcalc.py
shocktube1dcalc/solver_analytic.py
shocktube1dcalc-1.0.2.dist-info/LICENSE
shocktube1dcalc-1.0.2.dist-info/WHEEL
shocktube1dcalc-1.0.2.dist-info/METADATA
shocktube1dcalc-1.0.2.dist-info/RECORD
