Metadata-Version: 2.1
Name: shocktube1dcalc
Version: 1.0.2
Summary: 1D shocktube caculator to provide analytic solutions
Home-page: https://github.com/solvcon/shocktube1dcalc
License: BSD-3-Clause
Keywords: CFD,science
Author: Taihsiang Ho (tai271828)
Author-email: tai271828@gmail.com
Requires-Python: >=3.7,<4.0
Classifier: Development Status :: 6 - Mature
Classifier: Environment :: Console
Classifier: Intended Audience :: Science/Research
Classifier: License :: OSI Approved :: BSD License
Classifier: Natural Language :: English
Classifier: Operating System :: OS Independent
Classifier: Programming Language :: Python :: 3
Classifier: Programming Language :: Python :: 3 :: Only
Classifier: Programming Language :: Python :: 3.7
Classifier: Programming Language :: Python :: 3.8
Classifier: Programming Language :: Python :: 3.9
Classifier: Topic :: Scientific/Engineering :: Mathematics
Classifier: Topic :: Scientific/Engineering :: Physics
Classifier: Topic :: Software Development :: Libraries :: Python Modules
Classifier: Topic :: Utilities
Requires-Dist: ipython (>=7.19.0,<8.0.0)
Requires-Dist: matplotlib (>=3.3.3,<4.0.0)
Requires-Dist: numpy (>=1.19.5,<2.0.0)
Requires-Dist: scipy (>=1.6.0,<2.0.0)
Project-URL: Bug Tracker, https://github.com/solvcon/shocktube1dcalc/issues
Project-URL: Documentation, https://github.com/solvcon/shocktube1dcalc
Project-URL: Repository, https://github.com/solvcon/shocktube1dcalc
